spider_tools/__init__.py
spider_tools/__version__.py
spider_tools/core.py
spider_tools-0.1.1.dist-info/LICENSE
spider_tools-0.1.1.dist-info/METADATA
spider_tools-0.1.1.dist-info/WHEEL
spider_tools-0.1.1.dist-info/top_level.txt
spider_tools-0.1.1.dist-info/RECORD
