Metadata-Version: 2.1
Name: spider-tools
Version: 0.1.1
Summary: some of spider use tools.
Home-page: https://github.com/me/myproject
Author: zhang_Mr
Author-email: zclmbf597854439@gmail.com
License: MIT
Platform: UNKNOWN
Classifier: License :: OSI Approved :: MIT License
Classifier: Programming Language :: Python
Classifier: Programming Language :: Python :: 3
Classifier: Programming Language :: Python :: 3.6
Classifier: Programming Language :: Python :: Implementation :: CPython
Classifier: Programming Language :: Python :: Implementation :: PyPy
Requires-Python: >=3.1.0
